karelia.py
kareliapy-2.4.dist-info/LICENSE
kareliapy-2.4.dist-info/METADATA
kareliapy-2.4.dist-info/WHEEL
kareliapy-2.4.dist-info/top_level.txt
kareliapy-2.4.dist-info/RECORD
