Metadata-Version: 2.1
Name: kareliapy
Version: 2.4
Summary: Python library for euphoria.io
Home-page: https://github.com/struandw/karelia
Author: StruanDW
Author-email: struan@duncan-wilson.co.uk
License: UNKNOWN
Platform: UNKNOWN
Classifier: Programming Language :: Python :: 3
Classifier: License :: OSI Approved :: MIT License
Classifier: Operating System :: OS Independent
License-File: LICENSE
Requires-Dist: websocket-client
